.flake8
.gitignore
.travis.yml
LICENSE
Makefile
Pipfile
Pipfile.lock
README.md
setup.py
tox.ini
pytorch_pipeline/__init__.py
pytorch_pipeline/core.py
pytorch_pipeline/text.py
pytorch_pipeline.egg-info/PKG-INFO
pytorch_pipeline.egg-info/SOURCES.txt
pytorch_pipeline.egg-info/dependency_links.txt
pytorch_pipeline.egg-info/requires.txt
pytorch_pipeline.egg-info/top_level.txt
tests/__init__.py
tests/test_core.py
tests/test_text.py