Metadata-Version: 2.1
Name: pytorch-pipeline
Version: 0.0.1
Summary: Simple ETL Pipeline for PyTorch
Home-page: https://github.com/yasufumy/pytorch-pipeline
Author: Yasufumi Taniguchi
Author-email: yasufumi.taniguchi@gmail.com
License: MIT
Platform: UNKNOWN
Classifier: Programming Language :: Python :: 3.6
Classifier: Programming Language :: Python :: 3.7
Classifier: Programming Language :: Python :: 3.8
